volume_segmantics/__init__.py
volume_segmantics/data/__init__.py
volume_segmantics/data/augmentations.py
volume_segmantics/data/base_data_manager.py
volume_segmantics/data/dataloaders.py
volume_segmantics/data/datasets.py
volume_segmantics/data/pytorch3dunet_losses.py
volume_segmantics/data/pytorch3dunet_metrics.py
volume_segmantics/data/settings_data.py
volume_segmantics/data/slicers.py
volume_segmantics/model/__init__.py
volume_segmantics/model/model_2d.py
volume_segmantics/model/operations/vol_seg_2d_predictor.py
volume_segmantics/model/operations/vol_seg_2d_trainer.py
volume_segmantics/model/operations/vol_seg_prediction_manager.py
volume_segmantics/scripts/predict_2d_model.py
volume_segmantics/scripts/predict_2d_model_oo.py
volume_segmantics/scripts/train_2d_model.py
volume_segmantics/scripts/train_2d_model_oo.py
volume_segmantics/scripts/volume_segmantics
volume_segmantics/utilities/__init__.py
volume_segmantics/utilities/arg_parsing.py
volume_segmantics/utilities/base_data_utils.py
volume_segmantics/utilities/cmdline.py
volume_segmantics/utilities/config.py
volume_segmantics/utilities/early_stopping.py
volume_segmantics/utilities/pytorch3dunet_utils.py
volume_segmantics_vsui-0.3.6.dist-info/LICENSE.md
volume_segmantics_vsui-0.3.6.dist-info/METADATA
volume_segmantics_vsui-0.3.6.dist-info/WHEEL
volume_segmantics_vsui-0.3.6.dist-info/entry_points.txt
volume_segmantics_vsui-0.3.6.dist-info/RECORD
